cookieAI.py
cookieAI-2.3.7.dist-info/LICENSE
cookieAI-2.3.7.dist-info/METADATA
cookieAI-2.3.7.dist-info/WHEEL
cookieAI-2.3.7.dist-info/top_level.txt
cookieAI-2.3.7.dist-info/RECORD
