Metadata-Version: 2.1
Name: cookieAI
Version: 2.3.7
Summary: cookieAI Test Package for SQLShack Demo
Author: snj
Classifier: Programming Language :: Python :: 3
Classifier: License :: OSI Approved :: MIT License
Classifier: Operating System :: OS Independent
Requires-Python: >=3.6
License-File: LICENSE
